csv2shap/__init__.py
csv2shap/csv2shap.py
csv2shap-1.0.dist-info/LICENSE
csv2shap-1.0.dist-info/METADATA
csv2shap-1.0.dist-info/WHEEL
csv2shap-1.0.dist-info/top_level.txt
csv2shap-1.0.dist-info/RECORD
