Metadata-Version: 2.1
Name: csv2shap
Version: 1.0
Summary: 输入csv文件以及二分类的label名称，输出shap value图
Author: Dinghongyu
Author-email: dinghongyu1122@163.com
License-File: LICENSE
Requires-Dist: pandas
Requires-Dist: numpy
Requires-Dist: catboost
Requires-Dist: sklearn
Requires-Dist: Ipython
Requires-Dist: plotly
Requires-Dist: shap
Requires-Dist: matplotlib
Requires-Dist: seaborn
